<?xml version="1.0" encoding="UTF-8"?>
<INVENTORY>
  <ITEM>
    <ITEMTYPE>P</ITEMTYPE>
    <ITEMID>2431</ITEMID>
    <COLOR>85</COLOR>
    <MAXPRICE>-1.0000</MAXPRICE>
    <MINQTY>2</MINQTY>
    <CONDITION>N</CONDITION>
    <NOTIFY>N</NOTIFY>
  </ITEM>
  <ITEM>
    <ITEMTYPE>P</ITEMTYPE>
    <ITEMID>3024</ITEMID>
    <COLOR>86</COLOR>
    <MAXPRICE>-1.0000</MAXPRICE>
    <MINQTY>8</MINQTY>
    <CONDITION>N</CONDITION>
    <NOTIFY>N</NOTIFY>
  </ITEM>
  <ITEM>
    <ITEMTYPE>P</ITEMTYPE>
    <ITEMID>3035</ITEMID>
    <COLOR>85</COLOR>
    <MAXPRICE>-1.0000</MAXPRICE>
    <MINQTY>2</MINQTY>
    <CONDITION>N</CONDITION>
    <NOTIFY>N</NOTIFY>
  </ITEM>
  <ITEM>
    <ITEMTYPE>P</ITEMTYPE>
    <ITEMID>3062b</ITEMID>
    <COLOR>86</COLOR>
    <MAXPRICE>-1.0000</MAXPRICE>
    <MINQTY>54</MINQTY>
    <CONDITION>N</CONDITION>
    <NOTIFY>N</NOTIFY>
  </ITEM>
  <ITEM>
    <ITEMTYPE>P</ITEMTYPE>
    <ITEMID>32028</ITEMID>
    <COLOR>11</COLOR>
    <MAXPRICE>-1.0000</MAXPRICE>
    <MINQTY>6</MINQTY>
    <CONDITION>N</CONDITION>
    <NOTIFY>N</NOTIFY>
  </ITEM>
  <ITEM>
    <ITEMTYPE>P</ITEMTYPE>
    <ITEMID>4073</ITEMID>
    <COLOR>2</COLOR>
    <MAXPRICE>-1.0000</MAXPRICE>
    <MINQTY>25</MINQTY>
    <CONDITION>N</CONDITION>
    <NOTIFY>N</NOTIFY>
  </ITEM>
  <ITEM>
    <ITEMTYPE>P</ITEMTYPE>
    <ITEMID>4073</ITEMID>
    <COLOR>86</COLOR>
    <MAXPRICE>-1.0000</MAXPRICE>
    <MINQTY>37</MINQTY>
    <CONDITION>N</CONDITION>
    <NOTIFY>N</NOTIFY>
  </ITEM>
  <ITEM>
    <ITEMTYPE>P</ITEMTYPE>
    <ITEMID>4073</ITEMID>
    <COLOR>88</COLOR>
    <MAXPRICE>-1.0000</MAXPRICE>
    <MINQTY>25</MINQTY>
    <CONDITION>N</CONDITION>
    <NOTIFY>N</NOTIFY>
  </ITEM>
  <ITEM>
    <ITEMTYPE>P</ITEMTYPE>
    <ITEMID>4073</ITEMID>
    <COLOR>115</COLOR>
    <MAXPRICE>-1.0000</MAXPRICE>
    <MINQTY>110</MINQTY>
    <CONDITION>N</CONDITION>
    <NOTIFY>N</NOTIFY>
  </ITEM>
  <ITEM>
    <ITEMTYPE>P</ITEMTYPE>
    <ITEMID>30176</ITEMID>
    <COLOR>6</COLOR>
    <MAXPRICE>-1.0000</MAXPRICE>
    <MINQTY>10</MINQTY>
    <CONDITION>N</CONDITION>
    <NOTIFY>N</NOTIFY>
  </ITEM>
  <ITEM>
    <ITEMTYPE>P</ITEMTYPE>
    <ITEMID>6636</ITEMID>
    <COLOR>86</COLOR>
    <MAXPRICE>-1.0000</MAXPRICE>
    <MINQTY>6</MINQTY>
    <CONDITION>N</CONDITION>
    <NOTIFY>N</NOTIFY>
  </ITEM>
  <ITEM>
    <ITEMTYPE>P</ITEMTYPE>
    <ITEMID>3070b</ITEMID>
    <COLOR>85</COLOR>
    <MAXPRICE>-1.0000</MAXPRICE>
    <MINQTY>6</MINQTY>
    <CONDITION>N</CONDITION>
    <NOTIFY>N</NOTIFY>
  </ITEM>
  <ITEM>
    <ITEMTYPE>P</ITEMTYPE>
    <ITEMID>87087</ITEMID>
    <COLOR>1</COLOR>
    <MAXPRICE>-1.0000</MAXPRICE>
    <MINQTY>4</MINQTY>
    <CONDITION>N</CONDITION>
    <NOTIFY>N</NOTIFY>
  </ITEM>
  <ITEM>
    <ITEMTYPE>P</ITEMTYPE>
    <ITEMID>87087</ITEMID>
    <COLOR>11</COLOR>
    <MAXPRICE>-1.0000</MAXPRICE>
    <MINQTY>12</MINQTY>
    <CONDITION>N</CONDITION>
    <NOTIFY>N</NOTIFY>
  </ITEM>
  <ITEM>
    <ITEMTYPE>P</ITEMTYPE>
    <ITEMID>61252</ITEMID>
    <COLOR>86</COLOR>
    <MAXPRICE>-1.0000</MAXPRICE>
    <MINQTY>2</MINQTY>
    <CONDITION>N</CONDITION>
    <NOTIFY>N</NOTIFY>
  </ITEM>
  <ITEM>
    <ITEMTYPE>P</ITEMTYPE>
    <ITEMID>98138</ITEMID>
    <COLOR>115</COLOR>
    <MAXPRICE>-1.0000</MAXPRICE>
    <MINQTY>50</MINQTY>
    <CONDITION>N</CONDITION>
    <NOTIFY>N</NOTIFY>
  </ITEM>
  <ITEM>
    <ITEMTYPE>P</ITEMTYPE>
    <ITEMID>FTGpb022c01</ITEMID>
    <COLOR>90</COLOR>
    <MAXPRICE>-1.0000</MAXPRICE>
    <MINQTY>1</MINQTY>
    <CONDITION>N</CONDITION>
    <NOTIFY>N</NOTIFY>
  </ITEM>
  <ITEM>
    <ITEMTYPE>P</ITEMTYPE>
    <ITEMID>15573</ITEMID>
    <COLOR>11</COLOR>
    <MAXPRICE>-1.0000</MAXPRICE>
    <MINQTY>70</MINQTY>
    <CONDITION>N</CONDITION>
    <NOTIFY>N</NOTIFY>
  </ITEM>
  <ITEM>
    <ITEMTYPE>P</ITEMTYPE>
    <ITEMID>15573</ITEMID>
    <COLOR>85</COLOR>
    <MAXPRICE>-1.0000</MAXPRICE>
    <MINQTY>20</MINQTY>
    <CONDITION>N</CONDITION>
    <NOTIFY>N</NOTIFY>
  </ITEM>
  <ITEM>
    <ITEMTYPE>P</ITEMTYPE>
    <ITEMID>15068</ITEMID>
    <COLOR>85</COLOR>
    <MAXPRICE>-1.0000</MAXPRICE>
    <MINQTY>4</MINQTY>
    <CONDITION>N</CONDITION>
    <NOTIFY>N</NOTIFY>
  </ITEM>
  <ITEM>
    <ITEMTYPE>P</ITEMTYPE>
    <ITEMID>15332</ITEMID>
    <COLOR>11</COLOR>
    <MAXPRICE>-1.0000</MAXPRICE>
    <MINQTY>17</MINQTY>
    <CONDITION>N</CONDITION>
    <NOTIFY>N</NOTIFY>
  </ITEM>
  <ITEM>
    <ITEMTYPE>P</ITEMTYPE>
    <ITEMID>FTGpb038c01</ITEMID>
    <COLOR>90</COLOR>
    <MAXPRICE>-1.0000</MAXPRICE>
    <MINQTY>1</MINQTY>
    <CONDITION>N</CONDITION>
    <NOTIFY>N</NOTIFY>
  </ITEM>
  <ITEM>
    <ITEMTYPE>P</ITEMTYPE>
    <ITEMID>FTGpb087c01</ITEMID>
    <COLOR>90</COLOR>
    <MAXPRICE>-1.0000</MAXPRICE>
    <MINQTY>1</MINQTY>
    <CONDITION>N</CONDITION>
    <NOTIFY>N</NOTIFY>
  </ITEM>
  <ITEM>
    <ITEMTYPE>P</ITEMTYPE>
    <ITEMID>11640pb04</ITEMID>
    <COLOR>153</COLOR>
    <MAXPRICE>-1.0000</MAXPRICE>
    <MINQTY>1</MINQTY>
    <CONDITION>N</CONDITION>
    <NOTIFY>N</NOTIFY>
  </ITEM>
  <ITEM>
    <ITEMTYPE>P</ITEMTYPE>
    <ITEMID>15875c104pb001</ITEMID>
    <COLOR>47</COLOR>
    <MAXPRICE>-1.0000</MAXPRICE>
    <MINQTY>1</MINQTY>
    <CONDITION>N</CONDITION>
    <NOTIFY>N</NOTIFY>
  </ITEM>
</INVENTORY>
