<?xml version="1.0" encoding="UTF-8"?>
<INVENTORY>
  <ITEM>
    <ITEMTYPE>P</ITEMTYPE>
    <ITEMID>2431</ITEMID>
    <COLOR>5</COLOR>
    <MAXPRICE>-1.0000</MAXPRICE>
    <MINQTY>4</MINQTY>
    <CONDITION>N</CONDITION>
    <NOTIFY>N</NOTIFY>
  </ITEM>
  <ITEM>
    <ITEMTYPE>P</ITEMTYPE>
    <ITEMID>2431</ITEMID>
    <COLOR>34</COLOR>
    <MAXPRICE>-1.0000</MAXPRICE>
    <MINQTY>4</MINQTY>
    <CONDITION>N</CONDITION>
    <NOTIFY>N</NOTIFY>
  </ITEM>
  <ITEM>
    <ITEMTYPE>P</ITEMTYPE>
    <ITEMID>2431</ITEMID>
    <COLOR>156</COLOR>
    <MAXPRICE>-1.0000</MAXPRICE>
    <MINQTY>4</MINQTY>
    <CONDITION>N</CONDITION>
    <NOTIFY>N</NOTIFY>
  </ITEM>
  <ITEM>
    <ITEMTYPE>P</ITEMTYPE>
    <ITEMID>2479</ITEMID>
    <COLOR>11</COLOR>
    <MAXPRICE>-1.0000</MAXPRICE>
    <MINQTY>2</MINQTY>
    <CONDITION>N</CONDITION>
    <NOTIFY>N</NOTIFY>
  </ITEM>
  <ITEM>
    <ITEMTYPE>P</ITEMTYPE>
    <ITEMID>2926</ITEMID>
    <COLOR>11</COLOR>
    <MAXPRICE>-1.0000</MAXPRICE>
    <MINQTY>4</MINQTY>
    <CONDITION>N</CONDITION>
    <NOTIFY>N</NOTIFY>
  </ITEM>
  <ITEM>
    <ITEMTYPE>P</ITEMTYPE>
    <ITEMID>30000</ITEMID>
    <COLOR>85</COLOR>
    <MAXPRICE>-1.0000</MAXPRICE>
    <MINQTY>10</MINQTY>
    <CONDITION>N</CONDITION>
    <NOTIFY>N</NOTIFY>
  </ITEM>
  <ITEM>
    <ITEMTYPE>P</ITEMTYPE>
    <ITEMID>3001</ITEMID>
    <COLOR>1</COLOR>
    <MAXPRICE>-1.0000</MAXPRICE>
    <MINQTY>4</MINQTY>
    <CONDITION>N</CONDITION>
    <NOTIFY>N</NOTIFY>
  </ITEM>
  <ITEM>
    <ITEMTYPE>P</ITEMTYPE>
    <ITEMID>3001</ITEMID>
    <COLOR>5</COLOR>
    <MAXPRICE>-1.0000</MAXPRICE>
    <MINQTY>4</MINQTY>
    <CONDITION>N</CONDITION>
    <NOTIFY>N</NOTIFY>
  </ITEM>
  <ITEM>
    <ITEMTYPE>P</ITEMTYPE>
    <ITEMID>3001</ITEMID>
    <COLOR>6</COLOR>
    <MAXPRICE>-1.0000</MAXPRICE>
    <MINQTY>4</MINQTY>
    <CONDITION>N</CONDITION>
    <NOTIFY>N</NOTIFY>
  </ITEM>
  <ITEM>
    <ITEMTYPE>P</ITEMTYPE>
    <ITEMID>3001</ITEMID>
    <COLOR>7</COLOR>
    <MAXPRICE>-1.0000</MAXPRICE>
    <MINQTY>4</MINQTY>
    <CONDITION>N</CONDITION>
    <NOTIFY>N</NOTIFY>
  </ITEM>
  <ITEM>
    <ITEMTYPE>P</ITEMTYPE>
    <ITEMID>3001</ITEMID>
    <COLOR>34</COLOR>
    <MAXPRICE>-1.0000</MAXPRICE>
    <MINQTY>4</MINQTY>
    <CONDITION>N</CONDITION>
    <NOTIFY>N</NOTIFY>
  </ITEM>
  <ITEM>
    <ITEMTYPE>P</ITEMTYPE>
    <ITEMID>3001</ITEMID>
    <COLOR>80</COLOR>
    <MAXPRICE>-1.0000</MAXPRICE>
    <MINQTY>4</MINQTY>
    <CONDITION>N</CONDITION>
    <NOTIFY>N</NOTIFY>
  </ITEM>
  <ITEM>
    <ITEMTYPE>P</ITEMTYPE>
    <ITEMID>3001</ITEMID>
    <COLOR>85</COLOR>
    <MAXPRICE>-1.0000</MAXPRICE>
    <MINQTY>4</MINQTY>
    <CONDITION>N</CONDITION>
    <NOTIFY>N</NOTIFY>
  </ITEM>
  <ITEM>
    <ITEMTYPE>P</ITEMTYPE>
    <ITEMID>3001</ITEMID>
    <COLOR>88</COLOR>
    <MAXPRICE>-1.0000</MAXPRICE>
    <MINQTY>4</MINQTY>
    <CONDITION>N</CONDITION>
    <NOTIFY>N</NOTIFY>
  </ITEM>
  <ITEM>
    <ITEMTYPE>P</ITEMTYPE>
    <ITEMID>3001</ITEMID>
    <COLOR>89</COLOR>
    <MAXPRICE>-1.0000</MAXPRICE>
    <MINQTY>4</MINQTY>
    <CONDITION>N</CONDITION>
    <NOTIFY>N</NOTIFY>
  </ITEM>
  <ITEM>
    <ITEMTYPE>P</ITEMTYPE>
    <ITEMID>3001</ITEMID>
    <COLOR>104</COLOR>
    <MAXPRICE>-1.0000</MAXPRICE>
    <MINQTY>4</MINQTY>
    <CONDITION>N</CONDITION>
    <NOTIFY>N</NOTIFY>
  </ITEM>
  <ITEM>
    <ITEMTYPE>P</ITEMTYPE>
    <ITEMID>3001</ITEMID>
    <COLOR>110</COLOR>
    <MAXPRICE>-1.0000</MAXPRICE>
    <MINQTY>6</MINQTY>
    <CONDITION>N</CONDITION>
    <NOTIFY>N</NOTIFY>
  </ITEM>
  <ITEM>
    <ITEMTYPE>P</ITEMTYPE>
    <ITEMID>3001</ITEMID>
    <COLOR>153</COLOR>
    <MAXPRICE>-1.0000</MAXPRICE>
    <MINQTY>4</MINQTY>
    <CONDITION>N</CONDITION>
    <NOTIFY>N</NOTIFY>
  </ITEM>
  <ITEM>
    <ITEMTYPE>P</ITEMTYPE>
    <ITEMID>3001</ITEMID>
    <COLOR>157</COLOR>
    <MAXPRICE>-1.0000</MAXPRICE>
    <MINQTY>4</MINQTY>
    <CONDITION>N</CONDITION>
    <NOTIFY>N</NOTIFY>
  </ITEM>
  <ITEM>
    <ITEMTYPE>P</ITEMTYPE>
    <ITEMID>3002</ITEMID>
    <COLOR>4</COLOR>
    <MAXPRICE>-1.0000</MAXPRICE>
    <MINQTY>4</MINQTY>
    <CONDITION>N</CONDITION>
    <NOTIFY>N</NOTIFY>
  </ITEM>
  <ITEM>
    <ITEMTYPE>P</ITEMTYPE>
    <ITEMID>3002</ITEMID>
    <COLOR>88</COLOR>
    <MAXPRICE>-1.0000</MAXPRICE>
    <MINQTY>4</MINQTY>
    <CONDITION>N</CONDITION>
    <NOTIFY>N</NOTIFY>
  </ITEM>
  <ITEM>
    <ITEMTYPE>P</ITEMTYPE>
    <ITEMID>3003</ITEMID>
    <COLOR>3</COLOR>
    <MAXPRICE>-1.0000</MAXPRICE>
    <MINQTY>4</MINQTY>
    <CONDITION>N</CONDITION>
    <NOTIFY>N</NOTIFY>
  </ITEM>
  <ITEM>
    <ITEMTYPE>P</ITEMTYPE>
    <ITEMID>3003</ITEMID>
    <COLOR>6</COLOR>
    <MAXPRICE>-1.0000</MAXPRICE>
    <MINQTY>4</MINQTY>
    <CONDITION>N</CONDITION>
    <NOTIFY>N</NOTIFY>
  </ITEM>
  <ITEM>
    <ITEMTYPE>P</ITEMTYPE>
    <ITEMID>3003</ITEMID>
    <COLOR>47</COLOR>
    <MAXPRICE>-1.0000</MAXPRICE>
    <MINQTY>4</MINQTY>
    <CONDITION>N</CONDITION>
    <NOTIFY>N</NOTIFY>
  </ITEM>
  <ITEM>
    <ITEMTYPE>P</ITEMTYPE>
    <ITEMID>3003</ITEMID>
    <COLOR>59</COLOR>
    <MAXPRICE>-1.0000</MAXPRICE>
    <MINQTY>6</MINQTY>
    <CONDITION>N</CONDITION>
    <NOTIFY>N</NOTIFY>
  </ITEM>
  <ITEM>
    <ITEMTYPE>P</ITEMTYPE>
    <ITEMID>3003</ITEMID>
    <COLOR>86</COLOR>
    <MAXPRICE>-1.0000</MAXPRICE>
    <MINQTY>6</MINQTY>
    <CONDITION>N</CONDITION>
    <NOTIFY>N</NOTIFY>
  </ITEM>
  <ITEM>
    <ITEMTYPE>P</ITEMTYPE>
    <ITEMID>3004</ITEMID>
    <COLOR>1</COLOR>
    <MAXPRICE>-1.0000</MAXPRICE>
    <MINQTY>8</MINQTY>
    <CONDITION>N</CONDITION>
    <NOTIFY>N</NOTIFY>
  </ITEM>
  <ITEM>
    <ITEMTYPE>P</ITEMTYPE>
    <ITEMID>3004</ITEMID>
    <COLOR>4</COLOR>
    <MAXPRICE>-1.0000</MAXPRICE>
    <MINQTY>14</MINQTY>
    <CONDITION>N</CONDITION>
    <NOTIFY>N</NOTIFY>
  </ITEM>
  <ITEM>
    <ITEMTYPE>P</ITEMTYPE>
    <ITEMID>3004</ITEMID>
    <COLOR>34</COLOR>
    <MAXPRICE>-1.0000</MAXPRICE>
    <MINQTY>4</MINQTY>
    <CONDITION>N</CONDITION>
    <NOTIFY>N</NOTIFY>
  </ITEM>
  <ITEM>
    <ITEMTYPE>P</ITEMTYPE>
    <ITEMID>3004</ITEMID>
    <COLOR>59</COLOR>
    <MAXPRICE>-1.0000</MAXPRICE>
    <MINQTY>8</MINQTY>
    <CONDITION>N</CONDITION>
    <NOTIFY>N</NOTIFY>
  </ITEM>
  <ITEM>
    <ITEMTYPE>P</ITEMTYPE>
    <ITEMID>3004</ITEMID>
    <COLOR>63</COLOR>
    <MAXPRICE>-1.0000</MAXPRICE>
    <MINQTY>4</MINQTY>
    <CONDITION>N</CONDITION>
    <NOTIFY>N</NOTIFY>
  </ITEM>
  <ITEM>
    <ITEMTYPE>P</ITEMTYPE>
    <ITEMID>3004</ITEMID>
    <COLOR>68</COLOR>
    <MAXPRICE>-1.0000</MAXPRICE>
    <MINQTY>16</MINQTY>
    <CONDITION>N</CONDITION>
    <NOTIFY>N</NOTIFY>
  </ITEM>
  <ITEM>
    <ITEMTYPE>P</ITEMTYPE>
    <ITEMID>3004</ITEMID>
    <COLOR>80</COLOR>
    <MAXPRICE>-1.0000</MAXPRICE>
    <MINQTY>4</MINQTY>
    <CONDITION>N</CONDITION>
    <NOTIFY>N</NOTIFY>
  </ITEM>
  <ITEM>
    <ITEMTYPE>P</ITEMTYPE>
    <ITEMID>3004</ITEMID>
    <COLOR>103</COLOR>
    <MAXPRICE>-1.0000</MAXPRICE>
    <MINQTY>8</MINQTY>
    <CONDITION>N</CONDITION>
    <NOTIFY>N</NOTIFY>
  </ITEM>
  <ITEM>
    <ITEMTYPE>P</ITEMTYPE>
    <ITEMID>3004</ITEMID>
    <COLOR>110</COLOR>
    <MAXPRICE>-1.0000</MAXPRICE>
    <MINQTY>4</MINQTY>
    <CONDITION>N</CONDITION>
    <NOTIFY>N</NOTIFY>
  </ITEM>
  <ITEM>
    <ITEMTYPE>P</ITEMTYPE>
    <ITEMID>3004</ITEMID>
    <COLOR>152</COLOR>
    <MAXPRICE>-1.0000</MAXPRICE>
    <MINQTY>8</MINQTY>
    <CONDITION>N</CONDITION>
    <NOTIFY>N</NOTIFY>
  </ITEM>
  <ITEM>
    <ITEMTYPE>P</ITEMTYPE>
    <ITEMID>3004</ITEMID>
    <COLOR>153</COLOR>
    <MAXPRICE>-1.0000</MAXPRICE>
    <MINQTY>32</MINQTY>
    <CONDITION>N</CONDITION>
    <NOTIFY>N</NOTIFY>
  </ITEM>
  <ITEM>
    <ITEMTYPE>P</ITEMTYPE>
    <ITEMID>3004</ITEMID>
    <COLOR>158</COLOR>
    <MAXPRICE>-1.0000</MAXPRICE>
    <MINQTY>8</MINQTY>
    <CONDITION>N</CONDITION>
    <NOTIFY>N</NOTIFY>
  </ITEM>
  <ITEM>
    <ITEMTYPE>P</ITEMTYPE>
    <ITEMID>30044</ITEMID>
    <COLOR>2</COLOR>
    <MAXPRICE>-1.0000</MAXPRICE>
    <MINQTY>2</MINQTY>
    <CONDITION>N</CONDITION>
    <NOTIFY>N</NOTIFY>
  </ITEM>
  <ITEM>
    <ITEMTYPE>P</ITEMTYPE>
    <ITEMID>3005</ITEMID>
    <COLOR>4</COLOR>
    <MAXPRICE>-1.0000</MAXPRICE>
    <MINQTY>6</MINQTY>
    <CONDITION>N</CONDITION>
    <NOTIFY>N</NOTIFY>
  </ITEM>
  <ITEM>
    <ITEMTYPE>P</ITEMTYPE>
    <ITEMID>3005</ITEMID>
    <COLOR>7</COLOR>
    <MAXPRICE>-1.0000</MAXPRICE>
    <MINQTY>4</MINQTY>
    <CONDITION>N</CONDITION>
    <NOTIFY>N</NOTIFY>
  </ITEM>
  <ITEM>
    <ITEMTYPE>P</ITEMTYPE>
    <ITEMID>3005</ITEMID>
    <COLOR>11</COLOR>
    <MAXPRICE>-1.0000</MAXPRICE>
    <MINQTY>6</MINQTY>
    <CONDITION>N</CONDITION>
    <NOTIFY>N</NOTIFY>
  </ITEM>
  <ITEM>
    <ITEMTYPE>P</ITEMTYPE>
    <ITEMID>3007</ITEMID>
    <COLOR>5</COLOR>
    <MAXPRICE>-1.0000</MAXPRICE>
    <MINQTY>2</MINQTY>
    <CONDITION>N</CONDITION>
    <NOTIFY>N</NOTIFY>
  </ITEM>
  <ITEM>
    <ITEMTYPE>P</ITEMTYPE>
    <ITEMID>3007</ITEMID>
    <COLOR>86</COLOR>
    <MAXPRICE>-1.0000</MAXPRICE>
    <MINQTY>4</MINQTY>
    <CONDITION>N</CONDITION>
    <NOTIFY>N</NOTIFY>
  </ITEM>
  <ITEM>
    <ITEMTYPE>P</ITEMTYPE>
    <ITEMID>3009</ITEMID>
    <COLOR>3</COLOR>
    <MAXPRICE>-1.0000</MAXPRICE>
    <MINQTY>4</MINQTY>
    <CONDITION>N</CONDITION>
    <NOTIFY>N</NOTIFY>
  </ITEM>
  <ITEM>
    <ITEMTYPE>P</ITEMTYPE>
    <ITEMID>3009</ITEMID>
    <COLOR>156</COLOR>
    <MAXPRICE>-1.0000</MAXPRICE>
    <MINQTY>4</MINQTY>
    <CONDITION>N</CONDITION>
    <NOTIFY>N</NOTIFY>
  </ITEM>
  <ITEM>
    <ITEMTYPE>P</ITEMTYPE>
    <ITEMID>3010</ITEMID>
    <COLOR>2</COLOR>
    <MAXPRICE>-1.0000</MAXPRICE>
    <MINQTY>8</MINQTY>
    <CONDITION>N</CONDITION>
    <NOTIFY>N</NOTIFY>
  </ITEM>
  <ITEM>
    <ITEMTYPE>P</ITEMTYPE>
    <ITEMID>3010</ITEMID>
    <COLOR>7</COLOR>
    <MAXPRICE>-1.0000</MAXPRICE>
    <MINQTY>12</MINQTY>
    <CONDITION>N</CONDITION>
    <NOTIFY>N</NOTIFY>
  </ITEM>
  <ITEM>
    <ITEMTYPE>P</ITEMTYPE>
    <ITEMID>3010</ITEMID>
    <COLOR>34</COLOR>
    <MAXPRICE>-1.0000</MAXPRICE>
    <MINQTY>4</MINQTY>
    <CONDITION>N</CONDITION>
    <NOTIFY>N</NOTIFY>
  </ITEM>
  <ITEM>
    <ITEMTYPE>P</ITEMTYPE>
    <ITEMID>3010</ITEMID>
    <COLOR>71</COLOR>
    <MAXPRICE>-1.0000</MAXPRICE>
    <MINQTY>4</MINQTY>
    <CONDITION>N</CONDITION>
    <NOTIFY>N</NOTIFY>
  </ITEM>
  <ITEM>
    <ITEMTYPE>P</ITEMTYPE>
    <ITEMID>3010</ITEMID>
    <COLOR>154</COLOR>
    <MAXPRICE>-1.0000</MAXPRICE>
    <MINQTY>4</MINQTY>
    <CONDITION>N</CONDITION>
    <NOTIFY>N</NOTIFY>
  </ITEM>
  <ITEM>
    <ITEMTYPE>P</ITEMTYPE>
    <ITEMID>3010</ITEMID>
    <COLOR>156</COLOR>
    <MAXPRICE>-1.0000</MAXPRICE>
    <MINQTY>16</MINQTY>
    <CONDITION>N</CONDITION>
    <NOTIFY>N</NOTIFY>
  </ITEM>
  <ITEM>
    <ITEMTYPE>P</ITEMTYPE>
    <ITEMID>3020</ITEMID>
    <COLOR>1</COLOR>
    <MAXPRICE>-1.0000</MAXPRICE>
    <MINQTY>4</MINQTY>
    <CONDITION>N</CONDITION>
    <NOTIFY>N</NOTIFY>
  </ITEM>
  <ITEM>
    <ITEMTYPE>P</ITEMTYPE>
    <ITEMID>3020</ITEMID>
    <COLOR>4</COLOR>
    <MAXPRICE>-1.0000</MAXPRICE>
    <MINQTY>2</MINQTY>
    <CONDITION>N</CONDITION>
    <NOTIFY>N</NOTIFY>
  </ITEM>
  <ITEM>
    <ITEMTYPE>P</ITEMTYPE>
    <ITEMID>3020</ITEMID>
    <COLOR>11</COLOR>
    <MAXPRICE>-1.0000</MAXPRICE>
    <MINQTY>4</MINQTY>
    <CONDITION>N</CONDITION>
    <NOTIFY>N</NOTIFY>
  </ITEM>
  <ITEM>
    <ITEMTYPE>P</ITEMTYPE>
    <ITEMID>3020</ITEMID>
    <COLOR>86</COLOR>
    <MAXPRICE>-1.0000</MAXPRICE>
    <MINQTY>4</MINQTY>
    <CONDITION>N</CONDITION>
    <NOTIFY>N</NOTIFY>
  </ITEM>
  <ITEM>
    <ITEMTYPE>P</ITEMTYPE>
    <ITEMID>3021</ITEMID>
    <COLOR>3</COLOR>
    <MAXPRICE>-1.0000</MAXPRICE>
    <MINQTY>4</MINQTY>
    <CONDITION>N</CONDITION>
    <NOTIFY>N</NOTIFY>
  </ITEM>
  <ITEM>
    <ITEMTYPE>P</ITEMTYPE>
    <ITEMID>3021</ITEMID>
    <COLOR>6</COLOR>
    <MAXPRICE>-1.0000</MAXPRICE>
    <MINQTY>2</MINQTY>
    <CONDITION>N</CONDITION>
    <NOTIFY>N</NOTIFY>
  </ITEM>
  <ITEM>
    <ITEMTYPE>P</ITEMTYPE>
    <ITEMID>3022</ITEMID>
    <COLOR>5</COLOR>
    <MAXPRICE>-1.0000</MAXPRICE>
    <MINQTY>4</MINQTY>
    <CONDITION>N</CONDITION>
    <NOTIFY>N</NOTIFY>
  </ITEM>
  <ITEM>
    <ITEMTYPE>P</ITEMTYPE>
    <ITEMID>3023</ITEMID>
    <COLOR>5</COLOR>
    <MAXPRICE>-1.0000</MAXPRICE>
    <MINQTY>4</MINQTY>
    <CONDITION>N</CONDITION>
    <NOTIFY>N</NOTIFY>
  </ITEM>
  <ITEM>
    <ITEMTYPE>P</ITEMTYPE>
    <ITEMID>3023</ITEMID>
    <COLOR>59</COLOR>
    <MAXPRICE>-1.0000</MAXPRICE>
    <MINQTY>6</MINQTY>
    <CONDITION>N</CONDITION>
    <NOTIFY>N</NOTIFY>
  </ITEM>
  <ITEM>
    <ITEMTYPE>P</ITEMTYPE>
    <ITEMID>3023</ITEMID>
    <COLOR>89</COLOR>
    <MAXPRICE>-1.0000</MAXPRICE>
    <MINQTY>8</MINQTY>
    <CONDITION>N</CONDITION>
    <NOTIFY>N</NOTIFY>
  </ITEM>
  <ITEM>
    <ITEMTYPE>P</ITEMTYPE>
    <ITEMID>30236</ITEMID>
    <COLOR>11</COLOR>
    <MAXPRICE>-1.0000</MAXPRICE>
    <MINQTY>2</MINQTY>
    <CONDITION>N</CONDITION>
    <NOTIFY>N</NOTIFY>
  </ITEM>
  <ITEM>
    <ITEMTYPE>P</ITEMTYPE>
    <ITEMID>3031</ITEMID>
    <COLOR>7</COLOR>
    <MAXPRICE>-1.0000</MAXPRICE>
    <MINQTY>4</MINQTY>
    <CONDITION>N</CONDITION>
    <NOTIFY>N</NOTIFY>
  </ITEM>
  <ITEM>
    <ITEMTYPE>P</ITEMTYPE>
    <ITEMID>3031</ITEMID>
    <COLOR>36</COLOR>
    <MAXPRICE>-1.0000</MAXPRICE>
    <MINQTY>4</MINQTY>
    <CONDITION>N</CONDITION>
    <NOTIFY>N</NOTIFY>
  </ITEM>
  <ITEM>
    <ITEMTYPE>P</ITEMTYPE>
    <ITEMID>3032</ITEMID>
    <COLOR>63</COLOR>
    <MAXPRICE>-1.0000</MAXPRICE>
    <MINQTY>4</MINQTY>
    <CONDITION>N</CONDITION>
    <NOTIFY>N</NOTIFY>
  </ITEM>
  <ITEM>
    <ITEMTYPE>P</ITEMTYPE>
    <ITEMID>3034</ITEMID>
    <COLOR>6</COLOR>
    <MAXPRICE>-1.0000</MAXPRICE>
    <MINQTY>2</MINQTY>
    <CONDITION>N</CONDITION>
    <NOTIFY>N</NOTIFY>
  </ITEM>
  <ITEM>
    <ITEMTYPE>P</ITEMTYPE>
    <ITEMID>3035</ITEMID>
    <COLOR>3</COLOR>
    <MAXPRICE>-1.0000</MAXPRICE>
    <MINQTY>2</MINQTY>
    <CONDITION>N</CONDITION>
    <NOTIFY>N</NOTIFY>
  </ITEM>
  <ITEM>
    <ITEMTYPE>P</ITEMTYPE>
    <ITEMID>3036</ITEMID>
    <COLOR>85</COLOR>
    <MAXPRICE>-1.0000</MAXPRICE>
    <MINQTY>2</MINQTY>
    <CONDITION>N</CONDITION>
    <NOTIFY>N</NOTIFY>
  </ITEM>
  <ITEM>
    <ITEMTYPE>P</ITEMTYPE>
    <ITEMID>3037</ITEMID>
    <COLOR>59</COLOR>
    <MAXPRICE>-1.0000</MAXPRICE>
    <MINQTY>2</MINQTY>
    <CONDITION>N</CONDITION>
    <NOTIFY>N</NOTIFY>
  </ITEM>
  <ITEM>
    <ITEMTYPE>P</ITEMTYPE>
    <ITEMID>3039</ITEMID>
    <COLOR>1</COLOR>
    <MAXPRICE>-1.0000</MAXPRICE>
    <MINQTY>10</MINQTY>
    <CONDITION>N</CONDITION>
    <NOTIFY>N</NOTIFY>
  </ITEM>
  <ITEM>
    <ITEMTYPE>P</ITEMTYPE>
    <ITEMID>3039</ITEMID>
    <COLOR>4</COLOR>
    <MAXPRICE>-1.0000</MAXPRICE>
    <MINQTY>4</MINQTY>
    <CONDITION>N</CONDITION>
    <NOTIFY>N</NOTIFY>
  </ITEM>
  <ITEM>
    <ITEMTYPE>P</ITEMTYPE>
    <ITEMID>3039</ITEMID>
    <COLOR>7</COLOR>
    <MAXPRICE>-1.0000</MAXPRICE>
    <MINQTY>4</MINQTY>
    <CONDITION>N</CONDITION>
    <NOTIFY>N</NOTIFY>
  </ITEM>
  <ITEM>
    <ITEMTYPE>P</ITEMTYPE>
    <ITEMID>3039</ITEMID>
    <COLOR>12</COLOR>
    <MAXPRICE>-1.0000</MAXPRICE>
    <MINQTY>8</MINQTY>
    <CONDITION>N</CONDITION>
    <NOTIFY>N</NOTIFY>
  </ITEM>
  <ITEM>
    <ITEMTYPE>P</ITEMTYPE>
    <ITEMID>3040</ITEMID>
    <COLOR>2</COLOR>
    <MAXPRICE>-1.0000</MAXPRICE>
    <MINQTY>8</MINQTY>
    <CONDITION>N</CONDITION>
    <NOTIFY>N</NOTIFY>
  </ITEM>
  <ITEM>
    <ITEMTYPE>P</ITEMTYPE>
    <ITEMID>3040</ITEMID>
    <COLOR>4</COLOR>
    <MAXPRICE>-1.0000</MAXPRICE>
    <MINQTY>4</MINQTY>
    <CONDITION>N</CONDITION>
    <NOTIFY>N</NOTIFY>
  </ITEM>
  <ITEM>
    <ITEMTYPE>P</ITEMTYPE>
    <ITEMID>3040</ITEMID>
    <COLOR>5</COLOR>
    <MAXPRICE>-1.0000</MAXPRICE>
    <MINQTY>4</MINQTY>
    <CONDITION>N</CONDITION>
    <NOTIFY>N</NOTIFY>
  </ITEM>
  <ITEM>
    <ITEMTYPE>P</ITEMTYPE>
    <ITEMID>3040</ITEMID>
    <COLOR>6</COLOR>
    <MAXPRICE>-1.0000</MAXPRICE>
    <MINQTY>8</MINQTY>
    <CONDITION>N</CONDITION>
    <NOTIFY>N</NOTIFY>
  </ITEM>
  <ITEM>
    <ITEMTYPE>P</ITEMTYPE>
    <ITEMID>3040</ITEMID>
    <COLOR>7</COLOR>
    <MAXPRICE>-1.0000</MAXPRICE>
    <MINQTY>4</MINQTY>
    <CONDITION>N</CONDITION>
    <NOTIFY>N</NOTIFY>
  </ITEM>
  <ITEM>
    <ITEMTYPE>P</ITEMTYPE>
    <ITEMID>3040</ITEMID>
    <COLOR>11</COLOR>
    <MAXPRICE>-1.0000</MAXPRICE>
    <MINQTY>16</MINQTY>
    <CONDITION>N</CONDITION>
    <NOTIFY>N</NOTIFY>
  </ITEM>
  <ITEM>
    <ITEMTYPE>P</ITEMTYPE>
    <ITEMID>3040</ITEMID>
    <COLOR>34</COLOR>
    <MAXPRICE>-1.0000</MAXPRICE>
    <MINQTY>4</MINQTY>
    <CONDITION>N</CONDITION>
    <NOTIFY>N</NOTIFY>
  </ITEM>
  <ITEM>
    <ITEMTYPE>P</ITEMTYPE>
    <ITEMID>3040</ITEMID>
    <COLOR>68</COLOR>
    <MAXPRICE>-1.0000</MAXPRICE>
    <MINQTY>8</MINQTY>
    <CONDITION>N</CONDITION>
    <NOTIFY>N</NOTIFY>
  </ITEM>
  <ITEM>
    <ITEMTYPE>P</ITEMTYPE>
    <ITEMID>3040</ITEMID>
    <COLOR>80</COLOR>
    <MAXPRICE>-1.0000</MAXPRICE>
    <MINQTY>4</MINQTY>
    <CONDITION>N</CONDITION>
    <NOTIFY>N</NOTIFY>
  </ITEM>
  <ITEM>
    <ITEMTYPE>P</ITEMTYPE>
    <ITEMID>3040</ITEMID>
    <COLOR>104</COLOR>
    <MAXPRICE>-1.0000</MAXPRICE>
    <MINQTY>8</MINQTY>
    <CONDITION>N</CONDITION>
    <NOTIFY>N</NOTIFY>
  </ITEM>
  <ITEM>
    <ITEMTYPE>P</ITEMTYPE>
    <ITEMID>3040</ITEMID>
    <COLOR>157</COLOR>
    <MAXPRICE>-1.0000</MAXPRICE>
    <MINQTY>8</MINQTY>
    <CONDITION>N</CONDITION>
    <NOTIFY>N</NOTIFY>
  </ITEM>
  <ITEM>
    <ITEMTYPE>P</ITEMTYPE>
    <ITEMID>3062b</ITEMID>
    <COLOR>11</COLOR>
    <MAXPRICE>-1.0000</MAXPRICE>
    <MINQTY>4</MINQTY>
    <CONDITION>N</CONDITION>
    <NOTIFY>N</NOTIFY>
  </ITEM>
  <ITEM>
    <ITEMTYPE>P</ITEMTYPE>
    <ITEMID>3062b</ITEMID>
    <COLOR>68</COLOR>
    <MAXPRICE>-1.0000</MAXPRICE>
    <MINQTY>4</MINQTY>
    <CONDITION>N</CONDITION>
    <NOTIFY>N</NOTIFY>
  </ITEM>
  <ITEM>
    <ITEMTYPE>P</ITEMTYPE>
    <ITEMID>3065</ITEMID>
    <COLOR>19</COLOR>
    <MAXPRICE>-1.0000</MAXPRICE>
    <MINQTY>4</MINQTY>
    <CONDITION>N</CONDITION>
    <NOTIFY>N</NOTIFY>
  </ITEM>
  <ITEM>
    <ITEMTYPE>P</ITEMTYPE>
    <ITEMID>3065</ITEMID>
    <COLOR>50</COLOR>
    <MAXPRICE>-1.0000</MAXPRICE>
    <MINQTY>4</MINQTY>
    <CONDITION>N</CONDITION>
    <NOTIFY>N</NOTIFY>
  </ITEM>
  <ITEM>
    <ITEMTYPE>P</ITEMTYPE>
    <ITEMID>3065</ITEMID>
    <COLOR>108</COLOR>
    <MAXPRICE>-1.0000</MAXPRICE>
    <MINQTY>4</MINQTY>
    <CONDITION>N</CONDITION>
    <NOTIFY>N</NOTIFY>
  </ITEM>
  <ITEM>
    <ITEMTYPE>P</ITEMTYPE>
    <ITEMID>3184</ITEMID>
    <COLOR>11</COLOR>
    <MAXPRICE>-1.0000</MAXPRICE>
    <MINQTY>2</MINQTY>
    <CONDITION>N</CONDITION>
    <NOTIFY>N</NOTIFY>
  </ITEM>
  <ITEM>
    <ITEMTYPE>P</ITEMTYPE>
    <ITEMID>3622</ITEMID>
    <COLOR>4</COLOR>
    <MAXPRICE>-1.0000</MAXPRICE>
    <MINQTY>4</MINQTY>
    <CONDITION>N</CONDITION>
    <NOTIFY>N</NOTIFY>
  </ITEM>
  <ITEM>
    <ITEMTYPE>P</ITEMTYPE>
    <ITEMID>3623</ITEMID>
    <COLOR>2</COLOR>
    <MAXPRICE>-1.0000</MAXPRICE>
    <MINQTY>8</MINQTY>
    <CONDITION>N</CONDITION>
    <NOTIFY>N</NOTIFY>
  </ITEM>
  <ITEM>
    <ITEMTYPE>P</ITEMTYPE>
    <ITEMID>3659</ITEMID>
    <COLOR>120</COLOR>
    <MAXPRICE>-1.0000</MAXPRICE>
    <MINQTY>4</MINQTY>
    <CONDITION>N</CONDITION>
    <NOTIFY>N</NOTIFY>
  </ITEM>
  <ITEM>
    <ITEMTYPE>P</ITEMTYPE>
    <ITEMID>3660</ITEMID>
    <COLOR>6</COLOR>
    <MAXPRICE>-1.0000</MAXPRICE>
    <MINQTY>4</MINQTY>
    <CONDITION>N</CONDITION>
    <NOTIFY>N</NOTIFY>
  </ITEM>
  <ITEM>
    <ITEMTYPE>P</ITEMTYPE>
    <ITEMID>3660</ITEMID>
    <COLOR>7</COLOR>
    <MAXPRICE>-1.0000</MAXPRICE>
    <MINQTY>4</MINQTY>
    <CONDITION>N</CONDITION>
    <NOTIFY>N</NOTIFY>
  </ITEM>
  <ITEM>
    <ITEMTYPE>P</ITEMTYPE>
    <ITEMID>3665</ITEMID>
    <COLOR>7</COLOR>
    <MAXPRICE>-1.0000</MAXPRICE>
    <MINQTY>4</MINQTY>
    <CONDITION>N</CONDITION>
    <NOTIFY>N</NOTIFY>
  </ITEM>
  <ITEM>
    <ITEMTYPE>P</ITEMTYPE>
    <ITEMID>3665</ITEMID>
    <COLOR>11</COLOR>
    <MAXPRICE>-1.0000</MAXPRICE>
    <MINQTY>8</MINQTY>
    <CONDITION>N</CONDITION>
    <NOTIFY>N</NOTIFY>
  </ITEM>
  <ITEM>
    <ITEMTYPE>P</ITEMTYPE>
    <ITEMID>3665</ITEMID>
    <COLOR>85</COLOR>
    <MAXPRICE>-1.0000</MAXPRICE>
    <MINQTY>8</MINQTY>
    <CONDITION>N</CONDITION>
    <NOTIFY>N</NOTIFY>
  </ITEM>
  <ITEM>
    <ITEMTYPE>P</ITEMTYPE>
    <ITEMID>3666</ITEMID>
    <COLOR>156</COLOR>
    <MAXPRICE>-1.0000</MAXPRICE>
    <MINQTY>8</MINQTY>
    <CONDITION>N</CONDITION>
    <NOTIFY>N</NOTIFY>
  </ITEM>
  <ITEM>
    <ITEMTYPE>P</ITEMTYPE>
    <ITEMID>3679</ITEMID>
    <COLOR>86</COLOR>
    <MAXPRICE>-1.0000</MAXPRICE>
    <MINQTY>2</MINQTY>
    <CONDITION>N</CONDITION>
    <NOTIFY>N</NOTIFY>
  </ITEM>
  <ITEM>
    <ITEMTYPE>P</ITEMTYPE>
    <ITEMID>3680</ITEMID>
    <COLOR>5</COLOR>
    <MAXPRICE>-1.0000</MAXPRICE>
    <MINQTY>2</MINQTY>
    <CONDITION>N</CONDITION>
    <NOTIFY>N</NOTIFY>
  </ITEM>
  <ITEM>
    <ITEMTYPE>P</ITEMTYPE>
    <ITEMID>3710</ITEMID>
    <COLOR>3</COLOR>
    <MAXPRICE>-1.0000</MAXPRICE>
    <MINQTY>4</MINQTY>
    <CONDITION>N</CONDITION>
    <NOTIFY>N</NOTIFY>
  </ITEM>
  <ITEM>
    <ITEMTYPE>P</ITEMTYPE>
    <ITEMID>3710</ITEMID>
    <COLOR>59</COLOR>
    <MAXPRICE>-1.0000</MAXPRICE>
    <MINQTY>4</MINQTY>
    <CONDITION>N</CONDITION>
    <NOTIFY>N</NOTIFY>
  </ITEM>
  <ITEM>
    <ITEMTYPE>P</ITEMTYPE>
    <ITEMID>3710</ITEMID>
    <COLOR>63</COLOR>
    <MAXPRICE>-1.0000</MAXPRICE>
    <MINQTY>4</MINQTY>
    <CONDITION>N</CONDITION>
    <NOTIFY>N</NOTIFY>
  </ITEM>
  <ITEM>
    <ITEMTYPE>P</ITEMTYPE>
    <ITEMID>3710</ITEMID>
    <COLOR>68</COLOR>
    <MAXPRICE>-1.0000</MAXPRICE>
    <MINQTY>10</MINQTY>
    <CONDITION>N</CONDITION>
    <NOTIFY>N</NOTIFY>
  </ITEM>
  <ITEM>
    <ITEMTYPE>P</ITEMTYPE>
    <ITEMID>3710</ITEMID>
    <COLOR>86</COLOR>
    <MAXPRICE>-1.0000</MAXPRICE>
    <MINQTY>4</MINQTY>
    <CONDITION>N</CONDITION>
    <NOTIFY>N</NOTIFY>
  </ITEM>
  <ITEM>
    <ITEMTYPE>P</ITEMTYPE>
    <ITEMID>3795</ITEMID>
    <COLOR>1</COLOR>
    <MAXPRICE>-1.0000</MAXPRICE>
    <MINQTY>2</MINQTY>
    <CONDITION>N</CONDITION>
    <NOTIFY>N</NOTIFY>
  </ITEM>
  <ITEM>
    <ITEMTYPE>P</ITEMTYPE>
    <ITEMID>3795</ITEMID>
    <COLOR>34</COLOR>
    <MAXPRICE>-1.0000</MAXPRICE>
    <MINQTY>2</MINQTY>
    <CONDITION>N</CONDITION>
    <NOTIFY>N</NOTIFY>
  </ITEM>
  <ITEM>
    <ITEMTYPE>P</ITEMTYPE>
    <ITEMID>3941</ITEMID>
    <COLOR>3</COLOR>
    <MAXPRICE>-1.0000</MAXPRICE>
    <MINQTY>6</MINQTY>
    <CONDITION>N</CONDITION>
    <NOTIFY>N</NOTIFY>
  </ITEM>
  <ITEM>
    <ITEMTYPE>P</ITEMTYPE>
    <ITEMID>3941</ITEMID>
    <COLOR>5</COLOR>
    <MAXPRICE>-1.0000</MAXPRICE>
    <MINQTY>6</MINQTY>
    <CONDITION>N</CONDITION>
    <NOTIFY>N</NOTIFY>
  </ITEM>
  <ITEM>
    <ITEMTYPE>P</ITEMTYPE>
    <ITEMID>3941</ITEMID>
    <COLOR>6</COLOR>
    <MAXPRICE>-1.0000</MAXPRICE>
    <MINQTY>2</MINQTY>
    <CONDITION>N</CONDITION>
    <NOTIFY>N</NOTIFY>
  </ITEM>
  <ITEM>
    <ITEMTYPE>P</ITEMTYPE>
    <ITEMID>3941</ITEMID>
    <COLOR>88</COLOR>
    <MAXPRICE>-1.0000</MAXPRICE>
    <MINQTY>4</MINQTY>
    <CONDITION>N</CONDITION>
    <NOTIFY>N</NOTIFY>
  </ITEM>
  <ITEM>
    <ITEMTYPE>P</ITEMTYPE>
    <ITEMID>3941</ITEMID>
    <COLOR>89</COLOR>
    <MAXPRICE>-1.0000</MAXPRICE>
    <MINQTY>4</MINQTY>
    <CONDITION>N</CONDITION>
    <NOTIFY>N</NOTIFY>
  </ITEM>
  <ITEM>
    <ITEMTYPE>P</ITEMTYPE>
    <ITEMID>4032</ITEMID>
    <COLOR>3</COLOR>
    <MAXPRICE>-1.0000</MAXPRICE>
    <MINQTY>2</MINQTY>
    <CONDITION>N</CONDITION>
    <NOTIFY>N</NOTIFY>
  </ITEM>
  <ITEM>
    <ITEMTYPE>P</ITEMTYPE>
    <ITEMID>4070</ITEMID>
    <COLOR>6</COLOR>
    <MAXPRICE>-1.0000</MAXPRICE>
    <MINQTY>4</MINQTY>
    <CONDITION>N</CONDITION>
    <NOTIFY>N</NOTIFY>
  </ITEM>
  <ITEM>
    <ITEMTYPE>P</ITEMTYPE>
    <ITEMID>4070</ITEMID>
    <COLOR>85</COLOR>
    <MAXPRICE>-1.0000</MAXPRICE>
    <MINQTY>4</MINQTY>
    <CONDITION>N</CONDITION>
    <NOTIFY>N</NOTIFY>
  </ITEM>
  <ITEM>
    <ITEMTYPE>P</ITEMTYPE>
    <ITEMID>4073</ITEMID>
    <COLOR>1</COLOR>
    <MAXPRICE>-1.0000</MAXPRICE>
    <MINQTY>12</MINQTY>
    <CONDITION>N</CONDITION>
    <NOTIFY>N</NOTIFY>
  </ITEM>
  <ITEM>
    <ITEMTYPE>P</ITEMTYPE>
    <ITEMID>4073</ITEMID>
    <COLOR>3</COLOR>
    <MAXPRICE>-1.0000</MAXPRICE>
    <MINQTY>4</MINQTY>
    <CONDITION>N</CONDITION>
    <NOTIFY>N</NOTIFY>
  </ITEM>
  <ITEM>
    <ITEMTYPE>P</ITEMTYPE>
    <ITEMID>4073</ITEMID>
    <COLOR>11</COLOR>
    <MAXPRICE>-1.0000</MAXPRICE>
    <MINQTY>4</MINQTY>
    <CONDITION>N</CONDITION>
    <NOTIFY>N</NOTIFY>
  </ITEM>
  <ITEM>
    <ITEMTYPE>P</ITEMTYPE>
    <ITEMID>4073</ITEMID>
    <COLOR>12</COLOR>
    <MAXPRICE>-1.0000</MAXPRICE>
    <MINQTY>4</MINQTY>
    <CONDITION>N</CONDITION>
    <NOTIFY>N</NOTIFY>
  </ITEM>
  <ITEM>
    <ITEMTYPE>P</ITEMTYPE>
    <ITEMID>4073</ITEMID>
    <COLOR>17</COLOR>
    <MAXPRICE>-1.0000</MAXPRICE>
    <MINQTY>6</MINQTY>
    <CONDITION>N</CONDITION>
    <NOTIFY>N</NOTIFY>
  </ITEM>
  <ITEM>
    <ITEMTYPE>P</ITEMTYPE>
    <ITEMID>4286</ITEMID>
    <COLOR>6</COLOR>
    <MAXPRICE>-1.0000</MAXPRICE>
    <MINQTY>4</MINQTY>
    <CONDITION>N</CONDITION>
    <NOTIFY>N</NOTIFY>
  </ITEM>
  <ITEM>
    <ITEMTYPE>P</ITEMTYPE>
    <ITEMID>4600</ITEMID>
    <COLOR>11</COLOR>
    <MAXPRICE>-1.0000</MAXPRICE>
    <MINQTY>4</MINQTY>
    <CONDITION>N</CONDITION>
    <NOTIFY>N</NOTIFY>
  </ITEM>
  <ITEM>
    <ITEMTYPE>P</ITEMTYPE>
    <ITEMID>4624</ITEMID>
    <COLOR>86</COLOR>
    <MAXPRICE>-1.0000</MAXPRICE>
    <MINQTY>8</MINQTY>
    <CONDITION>N</CONDITION>
    <NOTIFY>N</NOTIFY>
  </ITEM>
  <ITEM>
    <ITEMTYPE>P</ITEMTYPE>
    <ITEMID>6091</ITEMID>
    <COLOR>5</COLOR>
    <MAXPRICE>-1.0000</MAXPRICE>
    <MINQTY>8</MINQTY>
    <CONDITION>N</CONDITION>
    <NOTIFY>N</NOTIFY>
  </ITEM>
  <ITEM>
    <ITEMTYPE>P</ITEMTYPE>
    <ITEMID>6091</ITEMID>
    <COLOR>47</COLOR>
    <MAXPRICE>-1.0000</MAXPRICE>
    <MINQTY>8</MINQTY>
    <CONDITION>N</CONDITION>
    <NOTIFY>N</NOTIFY>
  </ITEM>
  <ITEM>
    <ITEMTYPE>P</ITEMTYPE>
    <ITEMID>6091</ITEMID>
    <COLOR>156</COLOR>
    <MAXPRICE>-1.0000</MAXPRICE>
    <MINQTY>8</MINQTY>
    <CONDITION>N</CONDITION>
    <NOTIFY>N</NOTIFY>
  </ITEM>
  <ITEM>
    <ITEMTYPE>P</ITEMTYPE>
    <ITEMID>6215</ITEMID>
    <COLOR>1</COLOR>
    <MAXPRICE>-1.0000</MAXPRICE>
    <MINQTY>2</MINQTY>
    <CONDITION>N</CONDITION>
    <NOTIFY>N</NOTIFY>
  </ITEM>
  <ITEM>
    <ITEMTYPE>P</ITEMTYPE>
    <ITEMID>6215</ITEMID>
    <COLOR>5</COLOR>
    <MAXPRICE>-1.0000</MAXPRICE>
    <MINQTY>2</MINQTY>
    <CONDITION>N</CONDITION>
    <NOTIFY>N</NOTIFY>
  </ITEM>
  <ITEM>
    <ITEMTYPE>P</ITEMTYPE>
    <ITEMID>6232</ITEMID>
    <COLOR>2</COLOR>
    <MAXPRICE>-1.0000</MAXPRICE>
    <MINQTY>2</MINQTY>
    <CONDITION>N</CONDITION>
    <NOTIFY>N</NOTIFY>
  </ITEM>
  <ITEM>
    <ITEMTYPE>P</ITEMTYPE>
    <ITEMID>30414</ITEMID>
    <COLOR>3</COLOR>
    <MAXPRICE>-1.0000</MAXPRICE>
    <MINQTY>4</MINQTY>
    <CONDITION>N</CONDITION>
    <NOTIFY>N</NOTIFY>
  </ITEM>
  <ITEM>
    <ITEMTYPE>P</ITEMTYPE>
    <ITEMID>2412b</ITEMID>
    <COLOR>5</COLOR>
    <MAXPRICE>-1.0000</MAXPRICE>
    <MINQTY>4</MINQTY>
    <CONDITION>N</CONDITION>
    <NOTIFY>N</NOTIFY>
  </ITEM>
  <ITEM>
    <ITEMTYPE>P</ITEMTYPE>
    <ITEMID>2412b</ITEMID>
    <COLOR>86</COLOR>
    <MAXPRICE>-1.0000</MAXPRICE>
    <MINQTY>8</MINQTY>
    <CONDITION>N</CONDITION>
    <NOTIFY>N</NOTIFY>
  </ITEM>
  <ITEM>
    <ITEMTYPE>P</ITEMTYPE>
    <ITEMID>3069b</ITEMID>
    <COLOR>3</COLOR>
    <MAXPRICE>-1.0000</MAXPRICE>
    <MINQTY>8</MINQTY>
    <CONDITION>N</CONDITION>
    <NOTIFY>N</NOTIFY>
  </ITEM>
  <ITEM>
    <ITEMTYPE>P</ITEMTYPE>
    <ITEMID>44728</ITEMID>
    <COLOR>4</COLOR>
    <MAXPRICE>-1.0000</MAXPRICE>
    <MINQTY>2</MINQTY>
    <CONDITION>N</CONDITION>
    <NOTIFY>N</NOTIFY>
  </ITEM>
  <ITEM>
    <ITEMTYPE>P</ITEMTYPE>
    <ITEMID>44728</ITEMID>
    <COLOR>11</COLOR>
    <MAXPRICE>-1.0000</MAXPRICE>
    <MINQTY>2</MINQTY>
    <CONDITION>N</CONDITION>
    <NOTIFY>N</NOTIFY>
  </ITEM>
  <ITEM>
    <ITEMTYPE>P</ITEMTYPE>
    <ITEMID>6014b</ITEMID>
    <COLOR>86</COLOR>
    <MAXPRICE>-1.0000</MAXPRICE>
    <MINQTY>8</MINQTY>
    <CONDITION>N</CONDITION>
    <NOTIFY>N</NOTIFY>
  </ITEM>
  <ITEM>
    <ITEMTYPE>P</ITEMTYPE>
    <ITEMID>49668</ITEMID>
    <COLOR>1</COLOR>
    <MAXPRICE>-1.0000</MAXPRICE>
    <MINQTY>4</MINQTY>
    <CONDITION>N</CONDITION>
    <NOTIFY>N</NOTIFY>
  </ITEM>
  <ITEM>
    <ITEMTYPE>P</ITEMTYPE>
    <ITEMID>54200</ITEMID>
    <COLOR>4</COLOR>
    <MAXPRICE>-1.0000</MAXPRICE>
    <MINQTY>4</MINQTY>
    <CONDITION>N</CONDITION>
    <NOTIFY>N</NOTIFY>
  </ITEM>
  <ITEM>
    <ITEMTYPE>P</ITEMTYPE>
    <ITEMID>54200</ITEMID>
    <COLOR>80</COLOR>
    <MAXPRICE>-1.0000</MAXPRICE>
    <MINQTY>8</MINQTY>
    <CONDITION>N</CONDITION>
    <NOTIFY>N</NOTIFY>
  </ITEM>
  <ITEM>
    <ITEMTYPE>P</ITEMTYPE>
    <ITEMID>50950</ITEMID>
    <COLOR>86</COLOR>
    <MAXPRICE>-1.0000</MAXPRICE>
    <MINQTY>8</MINQTY>
    <CONDITION>N</CONDITION>
    <NOTIFY>N</NOTIFY>
  </ITEM>
  <ITEM>
    <ITEMTYPE>P</ITEMTYPE>
    <ITEMID>3747b</ITEMID>
    <COLOR>1</COLOR>
    <MAXPRICE>-1.0000</MAXPRICE>
    <MINQTY>4</MINQTY>
    <CONDITION>N</CONDITION>
    <NOTIFY>N</NOTIFY>
  </ITEM>
  <ITEM>
    <ITEMTYPE>P</ITEMTYPE>
    <ITEMID>3747b</ITEMID>
    <COLOR>4</COLOR>
    <MAXPRICE>-1.0000</MAXPRICE>
    <MINQTY>2</MINQTY>
    <CONDITION>N</CONDITION>
    <NOTIFY>N</NOTIFY>
  </ITEM>
  <ITEM>
    <ITEMTYPE>P</ITEMTYPE>
    <ITEMID>61678</ITEMID>
    <COLOR>154</COLOR>
    <MAXPRICE>-1.0000</MAXPRICE>
    <MINQTY>8</MINQTY>
    <CONDITION>N</CONDITION>
    <NOTIFY>N</NOTIFY>
  </ITEM>
  <ITEM>
    <ITEMTYPE>P</ITEMTYPE>
    <ITEMID>60478</ITEMID>
    <COLOR>1</COLOR>
    <MAXPRICE>-1.0000</MAXPRICE>
    <MINQTY>2</MINQTY>
    <CONDITION>N</CONDITION>
    <NOTIFY>N</NOTIFY>
  </ITEM>
  <ITEM>
    <ITEMTYPE>P</ITEMTYPE>
    <ITEMID>4589b</ITEMID>
    <COLOR>71</COLOR>
    <MAXPRICE>-1.0000</MAXPRICE>
    <MINQTY>4</MINQTY>
    <CONDITION>N</CONDITION>
    <NOTIFY>N</NOTIFY>
  </ITEM>
  <ITEM>
    <ITEMTYPE>P</ITEMTYPE>
    <ITEMID>4589b</ITEMID>
    <COLOR>85</COLOR>
    <MAXPRICE>-1.0000</MAXPRICE>
    <MINQTY>6</MINQTY>
    <CONDITION>N</CONDITION>
    <NOTIFY>N</NOTIFY>
  </ITEM>
  <ITEM>
    <ITEMTYPE>P</ITEMTYPE>
    <ITEMID>60481</ITEMID>
    <COLOR>120</COLOR>
    <MAXPRICE>-1.0000</MAXPRICE>
    <MINQTY>8</MINQTY>
    <CONDITION>N</CONDITION>
    <NOTIFY>N</NOTIFY>
  </ITEM>
  <ITEM>
    <ITEMTYPE>P</ITEMTYPE>
    <ITEMID>60032</ITEMID>
    <COLOR>2</COLOR>
    <MAXPRICE>-1.0000</MAXPRICE>
    <MINQTY>2</MINQTY>
    <CONDITION>N</CONDITION>
    <NOTIFY>N</NOTIFY>
  </ITEM>
  <ITEM>
    <ITEMTYPE>P</ITEMTYPE>
    <ITEMID>60032</ITEMID>
    <COLOR>11</COLOR>
    <MAXPRICE>-1.0000</MAXPRICE>
    <MINQTY>20</MINQTY>
    <CONDITION>N</CONDITION>
    <NOTIFY>N</NOTIFY>
  </ITEM>
  <ITEM>
    <ITEMTYPE>P</ITEMTYPE>
    <ITEMID>63868</ITEMID>
    <COLOR>3</COLOR>
    <MAXPRICE>-1.0000</MAXPRICE>
    <MINQTY>8</MINQTY>
    <CONDITION>N</CONDITION>
    <NOTIFY>N</NOTIFY>
  </ITEM>
  <ITEM>
    <ITEMTYPE>P</ITEMTYPE>
    <ITEMID>63868</ITEMID>
    <COLOR>11</COLOR>
    <MAXPRICE>-1.0000</MAXPRICE>
    <MINQTY>2</MINQTY>
    <CONDITION>N</CONDITION>
    <NOTIFY>N</NOTIFY>
  </ITEM>
  <ITEM>
    <ITEMTYPE>P</ITEMTYPE>
    <ITEMID>61254</ITEMID>
    <COLOR>11</COLOR>
    <MAXPRICE>-1.0000</MAXPRICE>
    <MINQTY>20</MINQTY>
    <CONDITION>N</CONDITION>
    <NOTIFY>N</NOTIFY>
  </ITEM>
  <ITEM>
    <ITEMTYPE>P</ITEMTYPE>
    <ITEMID>85984</ITEMID>
    <COLOR>5</COLOR>
    <MAXPRICE>-1.0000</MAXPRICE>
    <MINQTY>4</MINQTY>
    <CONDITION>N</CONDITION>
    <NOTIFY>N</NOTIFY>
  </ITEM>
  <ITEM>
    <ITEMTYPE>P</ITEMTYPE>
    <ITEMID>85984</ITEMID>
    <COLOR>152</COLOR>
    <MAXPRICE>-1.0000</MAXPRICE>
    <MINQTY>4</MINQTY>
    <CONDITION>N</CONDITION>
    <NOTIFY>N</NOTIFY>
  </ITEM>
  <ITEM>
    <ITEMTYPE>P</ITEMTYPE>
    <ITEMID>87580</ITEMID>
    <COLOR>7</COLOR>
    <MAXPRICE>-1.0000</MAXPRICE>
    <MINQTY>2</MINQTY>
    <CONDITION>N</CONDITION>
    <NOTIFY>N</NOTIFY>
  </ITEM>
  <ITEM>
    <ITEMTYPE>P</ITEMTYPE>
    <ITEMID>87580</ITEMID>
    <COLOR>34</COLOR>
    <MAXPRICE>-1.0000</MAXPRICE>
    <MINQTY>2</MINQTY>
    <CONDITION>N</CONDITION>
    <NOTIFY>N</NOTIFY>
  </ITEM>
  <ITEM>
    <ITEMTYPE>P</ITEMTYPE>
    <ITEMID>64799</ITEMID>
    <COLOR>3</COLOR>
    <MAXPRICE>-1.0000</MAXPRICE>
    <MINQTY>2</MINQTY>
    <CONDITION>N</CONDITION>
    <NOTIFY>N</NOTIFY>
  </ITEM>
  <ITEM>
    <ITEMTYPE>P</ITEMTYPE>
    <ITEMID>87087</ITEMID>
    <COLOR>152</COLOR>
    <MAXPRICE>-1.0000</MAXPRICE>
    <MINQTY>4</MINQTY>
    <CONDITION>N</CONDITION>
    <NOTIFY>N</NOTIFY>
  </ITEM>
  <ITEM>
    <ITEMTYPE>P</ITEMTYPE>
    <ITEMID>87087</ITEMID>
    <COLOR>153</COLOR>
    <MAXPRICE>-1.0000</MAXPRICE>
    <MINQTY>8</MINQTY>
    <CONDITION>N</CONDITION>
    <NOTIFY>N</NOTIFY>
  </ITEM>
  <ITEM>
    <ITEMTYPE>P</ITEMTYPE>
    <ITEMID>87079</ITEMID>
    <COLOR>63</COLOR>
    <MAXPRICE>-1.0000</MAXPRICE>
    <MINQTY>4</MINQTY>
    <CONDITION>N</CONDITION>
    <NOTIFY>N</NOTIFY>
  </ITEM>
  <ITEM>
    <ITEMTYPE>P</ITEMTYPE>
    <ITEMID>88930</ITEMID>
    <COLOR>7</COLOR>
    <MAXPRICE>-1.0000</MAXPRICE>
    <MINQTY>4</MINQTY>
    <CONDITION>N</CONDITION>
    <NOTIFY>N</NOTIFY>
  </ITEM>
  <ITEM>
    <ITEMTYPE>P</ITEMTYPE>
    <ITEMID>61252</ITEMID>
    <COLOR>3</COLOR>
    <MAXPRICE>-1.0000</MAXPRICE>
    <MINQTY>8</MINQTY>
    <CONDITION>N</CONDITION>
    <NOTIFY>N</NOTIFY>
  </ITEM>
  <ITEM>
    <ITEMTYPE>P</ITEMTYPE>
    <ITEMID>88292</ITEMID>
    <COLOR>1</COLOR>
    <MAXPRICE>-1.0000</MAXPRICE>
    <MINQTY>2</MINQTY>
    <CONDITION>N</CONDITION>
    <NOTIFY>N</NOTIFY>
  </ITEM>
  <ITEM>
    <ITEMTYPE>P</ITEMTYPE>
    <ITEMID>87697</ITEMID>
    <COLOR>11</COLOR>
    <MAXPRICE>-1.0000</MAXPRICE>
    <MINQTY>8</MINQTY>
    <CONDITION>N</CONDITION>
    <NOTIFY>N</NOTIFY>
  </ITEM>
  <ITEM>
    <ITEMTYPE>P</ITEMTYPE>
    <ITEMID>92438</ITEMID>
    <COLOR>36</COLOR>
    <MAXPRICE>-1.0000</MAXPRICE>
    <MINQTY>2</MINQTY>
    <CONDITION>N</CONDITION>
    <NOTIFY>N</NOTIFY>
  </ITEM>
  <ITEM>
    <ITEMTYPE>P</ITEMTYPE>
    <ITEMID>92947</ITEMID>
    <COLOR>11</COLOR>
    <MAXPRICE>-1.0000</MAXPRICE>
    <MINQTY>2</MINQTY>
    <CONDITION>N</CONDITION>
    <NOTIFY>N</NOTIFY>
  </ITEM>
  <ITEM>
    <ITEMTYPE>P</ITEMTYPE>
    <ITEMID>4460b</ITEMID>
    <COLOR>86</COLOR>
    <MAXPRICE>-1.0000</MAXPRICE>
    <MINQTY>4</MINQTY>
    <CONDITION>N</CONDITION>
    <NOTIFY>N</NOTIFY>
  </ITEM>
  <ITEM>
    <ITEMTYPE>P</ITEMTYPE>
    <ITEMID>87414</ITEMID>
    <COLOR>11</COLOR>
    <MAXPRICE>-1.0000</MAXPRICE>
    <MINQTY>8</MINQTY>
    <CONDITION>N</CONDITION>
    <NOTIFY>N</NOTIFY>
  </ITEM>
  <ITEM>
    <ITEMTYPE>P</ITEMTYPE>
    <ITEMID>94161</ITEMID>
    <COLOR>88</COLOR>
    <MAXPRICE>-1.0000</MAXPRICE>
    <MINQTY>2</MINQTY>
    <CONDITION>N</CONDITION>
    <NOTIFY>N</NOTIFY>
  </ITEM>
  <ITEM>
    <ITEMTYPE>P</ITEMTYPE>
    <ITEMID>93273</ITEMID>
    <COLOR>7</COLOR>
    <MAXPRICE>-1.0000</MAXPRICE>
    <MINQTY>4</MINQTY>
    <CONDITION>N</CONDITION>
    <NOTIFY>N</NOTIFY>
  </ITEM>
  <ITEM>
    <ITEMTYPE>P</ITEMTYPE>
    <ITEMID>96874</ITEMID>
    <COLOR>4</COLOR>
    <MAXPRICE>-1.0000</MAXPRICE>
    <MINQTY>2</MINQTY>
    <CONDITION>N</CONDITION>
    <NOTIFY>N</NOTIFY>
  </ITEM>
  <ITEM>
    <ITEMTYPE>P</ITEMTYPE>
    <ITEMID>98263</ITEMID>
    <COLOR>86</COLOR>
    <MAXPRICE>-1.0000</MAXPRICE>
    <MINQTY>4</MINQTY>
    <CONDITION>N</CONDITION>
    <NOTIFY>N</NOTIFY>
  </ITEM>
  <ITEM>
    <ITEMTYPE>P</ITEMTYPE>
    <ITEMID>3684c</ITEMID>
    <COLOR>86</COLOR>
    <MAXPRICE>-1.0000</MAXPRICE>
    <MINQTY>4</MINQTY>
    <CONDITION>N</CONDITION>
    <NOTIFY>N</NOTIFY>
  </ITEM>
  <ITEM>
    <ITEMTYPE>P</ITEMTYPE>
    <ITEMID>98138pb007</ITEMID>
    <COLOR>1</COLOR>
    <MAXPRICE>-1.0000</MAXPRICE>
    <MINQTY>4</MINQTY>
    <CONDITION>N</CONDITION>
    <NOTIFY>N</NOTIFY>
  </ITEM>
  <ITEM>
    <ITEMTYPE>P</ITEMTYPE>
    <ITEMID>75937</ITEMID>
    <COLOR>1</COLOR>
    <MAXPRICE>-1.0000</MAXPRICE>
    <MINQTY>2</MINQTY>
    <CONDITION>N</CONDITION>
    <NOTIFY>N</NOTIFY>
  </ITEM>
  <ITEM>
    <ITEMTYPE>P</ITEMTYPE>
    <ITEMID>98100</ITEMID>
    <COLOR>11</COLOR>
    <MAXPRICE>-1.0000</MAXPRICE>
    <MINQTY>2</MINQTY>
    <CONDITION>N</CONDITION>
    <NOTIFY>N</NOTIFY>
  </ITEM>
  <ITEM>
    <ITEMTYPE>P</ITEMTYPE>
    <ITEMID>11477</ITEMID>
    <COLOR>5</COLOR>
    <MAXPRICE>-1.0000</MAXPRICE>
    <MINQTY>4</MINQTY>
    <CONDITION>N</CONDITION>
    <NOTIFY>N</NOTIFY>
  </ITEM>
  <ITEM>
    <ITEMTYPE>P</ITEMTYPE>
    <ITEMID>13971</ITEMID>
    <COLOR>86</COLOR>
    <MAXPRICE>-1.0000</MAXPRICE>
    <MINQTY>20</MINQTY>
    <CONDITION>N</CONDITION>
    <NOTIFY>N</NOTIFY>
  </ITEM>
  <ITEM>
    <ITEMTYPE>P</ITEMTYPE>
    <ITEMID>15573</ITEMID>
    <COLOR>4</COLOR>
    <MAXPRICE>-1.0000</MAXPRICE>
    <MINQTY>2</MINQTY>
    <CONDITION>N</CONDITION>
    <NOTIFY>N</NOTIFY>
  </ITEM>
  <ITEM>
    <ITEMTYPE>P</ITEMTYPE>
    <ITEMID>15397</ITEMID>
    <COLOR>1</COLOR>
    <MAXPRICE>-1.0000</MAXPRICE>
    <MINQTY>2</MINQTY>
    <CONDITION>N</CONDITION>
    <NOTIFY>N</NOTIFY>
  </ITEM>
  <ITEM>
    <ITEMTYPE>P</ITEMTYPE>
    <ITEMID>98138pb027</ITEMID>
    <COLOR>1</COLOR>
    <MAXPRICE>-1.0000</MAXPRICE>
    <MINQTY>4</MINQTY>
    <CONDITION>N</CONDITION>
    <NOTIFY>N</NOTIFY>
  </ITEM>
  <ITEM>
    <ITEMTYPE>P</ITEMTYPE>
    <ITEMID>98138pb028</ITEMID>
    <COLOR>1</COLOR>
    <MAXPRICE>-1.0000</MAXPRICE>
    <MINQTY>4</MINQTY>
    <CONDITION>N</CONDITION>
    <NOTIFY>N</NOTIFY>
  </ITEM>
</INVENTORY>
